core/__init__.py
core/__main__.py
core/config.py
core/api/__init__.py
core/api/analyze.py
core/api/assess.py
core/api/assets.py
core/api/auth.py
core/api/bots.py
core/api/collectors.py
core/api/config.py
core/api/dashboard.py
core/api/isalive.py
core/api/keycloak.py
core/api/presenters.py
core/api/publish.py
core/api/publishers.py
core/api/remote.py
core/api/user.py
core/auth/__init__.py
core/auth/base_authenticator.py
core/auth/database_authenticator.py
core/auth/keycloak_authenticator.py
core/auth/openid_authenticator.py
core/auth/test_authenticator.py
core/managers/__init__.py
core/managers/api_manager.py
core/managers/asset_manager.py
core/managers/audit_manager.py
core/managers/auth_manager.py
core/managers/bots_manager.py
core/managers/collectors_manager.py
core/managers/db_manager.py
core/managers/db_seed_manager.py
core/managers/external_auth_manager.py
core/managers/log_manager.py
core/managers/presenters_manager.py
core/managers/publishers_manager.py
core/managers/remote_manager.py
core/managers/sse_manager.py
core/managers/tagcloud_manager.py
core/managers/time_manager.py
core/managers/workers_pre_seed.py
core/model/__init__.py
core/model/acl_entry.py
core/model/address.py
core/model/asset.py
core/model/attribute.py
core/model/audit_record.py
core/model/bot.py
core/model/bots_node.py
core/model/collector.py
core/model/collectors_node.py
core/model/news_item.py
core/model/notification_template.py
core/model/organization.py
core/model/osint_source.py
core/model/parameter.py
core/model/parameter_value.py
core/model/permission.py
core/model/presenter.py
core/model/presenters_node.py
core/model/product.py
core/model/product_type.py
core/model/publisher.py
core/model/publisher_preset.py
core/model/publishers_node.py
core/model/remote.py
core/model/report_item.py
core/model/report_item_type.py
core/model/role.py
core/model/tag_cloud.py
core/model/token_blacklist.py
core/model/user.py
core/model/word_list.py
core/remote/__init__.py
core/remote/bots_api.py
taranis_ng_core-0.1.6.dist-info/METADATA
taranis_ng_core-0.1.6.dist-info/WHEEL
taranis_ng_core-0.1.6.dist-info/top_level.txt
taranis_ng_core-0.1.6.dist-info/RECORD
