Metadata-Version: 2.1
Name: taranis-ng-core
Version: 0.1.6
Summary: Taranis-NG Core
Home-page: https://github.com/SK-CERT/Taranis-NG
Author: SK-CERT, AIT
License: EUPL
Platform: any
Classifier: Programming Language :: Python
Classifier: Programming Language :: Python :: 3
Classifier: Programming Language :: Python :: 3.7
Classifier: Programming Language :: Python :: 3.8
Classifier: Programming Language :: Python :: 3.9
Classifier: Programming Language :: Python :: 3.10
Classifier: Topic :: Security
Requires-Python: >=3.7
Requires-Dist: Flask
Requires-Dist: Flask-Cors
Requires-Dist: Flask-JWT-Extended
Requires-Dist: Flask-Migrate
Requires-Dist: Flask-RESTful
Requires-Dist: Flask-SQLAlchemy (==2.5.1)
Requires-Dist: Flask-SSE
Requires-Dist: SQLAlchemy (==1.4.40)
Requires-Dist: click
Requires-Dist: pydantic
Requires-Dist: python-dotenv
Requires-Dist: gevent
Requires-Dist: gunicorn
Requires-Dist: psycogreen
Requires-Dist: psycopg2
Requires-Dist: marshmallow
Requires-Dist: marshmallow-enum
Requires-Dist: taranis-ng-shared
Requires-Dist: dateparser
Requires-Dist: swagger-ui-py
Requires-Dist: tzdata
Requires-Dist: tzlocal
Requires-Dist: requests
Requires-Dist: requests-oauthlib
Requires-Dist: Deprecated
Requires-Dist: schedule
Requires-Dist: Authlib
Requires-Dist: oauthlib
Requires-Dist: pyparsing
Requires-Dist: python-keycloak
Requires-Dist: sseclient-py
